[{"group":"Nondemented","sex":"M","age":87,"educ":14,"ses":2.0,"mmse":27.0,"cdr":0.0,"nwbv":0.696},{"group":"Nondemented","sex":"M","age":88,"educ":14,"ses":2.0,"mmse":30.0,"cdr":0.0,"nwbv":0.681},{"group":"Demented","sex":"M","age":75,"educ":12,"ses":null,"mmse":23.0,"cdr":0.5,"nwbv":0.736},{"group":"Demented","sex":"M","age":76,"educ":12,"ses":null,"mmse":28.0,"cdr":0.5,"nwbv":0.713},{"group":"Demented","sex":"M","age":80,"educ":12,"ses":null,"mmse":22.0,"cdr":0.5,"nwbv":0.701},{"group":"Nondemented","sex":"F","age":88,"educ":18,"ses":3.0,"mmse":28.0,"cdr":0.0,"nwbv":0.71},{"group":"Nondemented","sex":"F","age":90,"educ":18,"ses":3.0,"mmse":27.0,"cdr":0.0,"nwbv":0.718},{"group":"Nondemented","sex":"M","age":80,"educ":12,"ses":4.0,"mmse":28.0,"cdr":0.0,"nwbv":0.712},{"group":"Nondemented","sex":"M","age":83,"educ":12,"ses":4.0,"mmse":29.0,"cdr":0.5,"nwbv":0.711},{"group":"Nondemented","sex":"M","age":85,"educ":12,"ses":4.0,"mmse":30.0,"cdr":0.0,"nwbv":0.705},{"group":"Demented","sex":"M","age":71,"educ":16,"ses":null,"mmse":28.0,"cdr":0.5,"nwbv":0.748},{"group":"Demented","sex":"M","age":73,"educ":16,"ses":null,"mmse":27.0,"cdr":1.0,"nwbv":0.727},{"group":"Demented","sex":"M","age":75,"educ":16,"ses":null,"mmse":27.0,"cdr":1.0,"nwbv":0.71},{"group":"Nondemented","sex":"F","age":93,"educ":14,"ses":2.0,"mmse":30.0,"cdr":0.0,"nwbv":0.698},{"group":"Nondemented","sex":"F","age":95,"educ":14,"ses":2.0,"mmse":29.0,"cdr":0.0,"nwbv":0.703},{"group":"Demented","sex":"M","age":68,"educ":12,"ses":2.0,"mmse":27.0,"cdr":0.5,"nwbv":0.806},{"group":"Demented","sex":"M","age":69,"educ":12,"ses":2.0,"mmse":24.0,"cdr":0.5,"nwbv":0.791},{"group":"Demented","sex":"F","age":66,"educ":12,"ses":3.0,"mmse":30.0,"cdr":0.5,"nwbv":0.769},{"group":"Demented","sex":"F","age":68,"educ":12,"ses":3.0,"mmse":29.0,"cdr":0.5,"nwbv":0.752},{"group":"Nondemented","sex":"F","age":78,"educ":16,"ses":2.0,"mmse":29.0,"cdr":0.0,"nwbv":0.748},{"group":"Nondemented","sex":"F","age":80,"educ":16,"ses":2.0,"mmse":29.0,"cdr":0.0,"nwbv":0.738},{"group":"Nondemented","sex":"F","age":83,"educ":16,"ses":2.0,"mmse":29.0,"cdr":0.0,"nwbv":0.718},{"group":"Nondemented","sex":"F","age":81,"educ":12,"ses":4.0,"mmse":30.0,"cdr":0.0,"nwbv":0.715},{"group":"Nondemented","sex":"F","age":82,"educ":12,"ses":4.0,"mmse":30.0,"cdr":0.0,"nwbv":0.72},{"group":"Nondemented","sex":"F","age":85,"educ":12,"ses":4.0,"mmse":29.0,"cdr":0.0,"nwbv":0.71},{"group":"Demented","sex":"M","age":76,"educ":16,"ses":3.0,"mmse":21.0,"cdr":0.5,"nwbv":0.697},{"group":"Demented","sex":"M","age":77,"educ":16,"ses":3.0,"mmse":16.0,"cdr":1.0,"nwbv":0.696},{"group":"Demented","sex":"M","age":88,"educ":8,"ses":4.0,"mmse":25.0,"cdr":0.5,"nwbv":0.66},{"group":"Demented","sex":"M","age":90,"educ":8,"ses":4.0,"mmse":23.0,"cdr":0.5,"nwbv":0.646},{"group":"Nondemented","sex":"M","age":80,"educ":12,"ses":3.0,"mmse":29.0,"cdr":0.0,"nwbv":0.752},{"group":"Nondemented","sex":"M","age":81,"educ":12,"ses":3.0,"mmse":27.0,"cdr":0.5,"nwbv":0.759},{"group":"Nondemented","sex":"M","age":85,"educ":12,"ses":3.0,"mmse":30.0,"cdr":0.0,"nwbv":0.755},{"group":"Nondemented","sex":"M","age":86,"educ":12,"ses":3.0,"mmse":27.0,"cdr":0.0,"nwbv":0.761},{"group":"Converted","sex":"F","age":87,"educ":14,"ses":1.0,"mmse":30.0,"cdr":0.0,"nwbv":0.715},{"group":"Converted","sex":"F","age":88,"educ":14,"ses":1.0,"mmse":29.0,"cdr":0.0,"nwbv":0.713},{"group":"Converted","sex":"F","age":92,"educ":14,"ses":1.0,"mmse":27.0,"cdr":0.5,"nwbv":0.696},{"group":"Converted","sex":"M","age":80,"educ":20,"ses":1.0,"mmse":29.0,"cdr":0.0,"nwbv":0.693},{"group":"Converted","sex":"M","age":82,"educ":20,"ses":1.0,"mmse":28.0,"cdr":0.5,"nwbv":0.677},{"group":"Converted","sex":"M","age":84,"educ":20,"ses":1.0,"mmse":26.0,"cdr":0.5,"nwbv":0.666},{"group":"Demented","sex":"M","age":72,"educ":20,"ses":1.0,"mmse":26.0,"cdr":0.5,"nwbv":0.719},{"group":"Demented","sex":"M","age":76,"educ":20,"ses":1.0,"mmse":25.0,"cdr":0.5,"nwbv":0.736},{"group":"Nondemented","sex":"F","age":61,"educ":16,"ses":3.0,"mmse":30.0,"cdr":0.0,"nwbv":0.805},{"group":"Nondemented","sex":"F","age":64,"educ":16,"ses":3.0,"mmse":29.0,"cdr":0.0,"nwbv":0.796},{"group":"Demented","sex":"F","age":86,"educ":12,"ses":4.0,"mmse":21.0,"cdr":0.5,"nwbv":0.662},{"group":"Demented","sex":"F","age":87,"educ":12,"ses":4.0,"mmse":21.0,"cdr":0.5,"nwbv":0.652},{"group":"Demented","sex":"M","age":82,"educ":12,"ses":3.0,"mmse":27.0,"cdr":0.5,"nwbv":0.713},{"group":"Demented","sex":"M","age":84,"educ":12,"ses":3.0,"mmse":27.0,"cdr":0.5,"nwbv":0.695},{"group":"Nondemented","sex":"F","age":69,"educ":12,"ses":3.0,"mmse":29.0,"cdr":0.0,"nwbv":0.783},{"group":"Nondemented","sex":"F","age":71,"educ":12,"ses":3.0,"mmse":30.0,"cdr":0.0,"nwbv":0.782},{"group":"Nondemented","sex":"F","age":73,"educ":12,"ses":3.0,"mmse":30.0,"cdr":0.0,"nwbv":0.775},{"group":"Nondemented","sex":"F","age":74,"educ":12,"ses":3.0,"mmse":30.0,"cdr":0.0,"nwbv":0.772},{"group":"Demented","sex":"M","age":64,"educ":18,"ses":2.0,"mmse":22.0,"cdr":0.5,"nwbv":0.737},{"group":"Demented","sex":"M","age":66,"educ":18,"ses":2.0,"mmse":21.0,"cdr":1.0,"nwbv":0.717},{"group":"Nondemented","sex":"F","age":77,"educ":12,"ses":4.0,"mmse":29.0,"cdr":0.0,"nwbv":0.734},{"group":"Nondemented","sex":"F","age":80,"educ":12,"ses":4.0,"mmse":30.0,"cdr":0.0,"nwbv":0.735},{"group":"Nondemented","sex":"F","age":60,"educ":18,"ses":1.0,"mmse":30.0,"cdr":0.0,"nwbv":0.822},{"group":"Nondemented","sex":"F","age":62,"educ":18,"ses":1.0,"mmse":30.0,"cdr":0.0,"nwbv":0.817},{"group":"Converted","sex":"F","age":86,"educ":12,"ses":3.0,"mmse":30.0,"cdr":0.0,"nwbv":0.718},{"group":"Converted","sex":"F","age":88,"educ":12,"ses":3.0,"mmse":30.0,"cdr":0.0,"nwbv":0.719},{"group":"Converted","sex":"F","age":91,"educ":12,"ses":3.0,"mmse":28.0,"cdr":0.5,"nwbv":0.696},{"group":"Demented","sex":"M","age":90,"educ":12,"ses":3.0,"mmse":21.0,"cdr":0.5,"nwbv":0.679},{"group":"Demented","sex":"M","age":92,"educ":12,"ses":3.0,"mmse":24.0,"cdr":0.5,"nwbv":0.676},{"group":"Nondemented","sex":"F","age":79,"educ":16,"ses":1.0,"mmse":29.0,"cdr":0.0,"nwbv":0.703},{"group":"Nondemented","sex":"F","age":80,"educ":16,"ses":1.0,"mmse":30.0,"cdr":0.0,"nwbv":0.698},{"group":"Nondemented","sex":"F","age":82,"educ":16,"ses":1.0,"mmse":30.0,"cdr":0.0,"nwbv":0.695},{"group":"Nondemented","sex":"F","age":84,"educ":16,"ses":1.0,"mmse":30.0,"cdr":0.0,"nwbv":0.684},{"group":"Nondemented","sex":"F","age":88,"educ":12,"ses":4.0,"mmse":30.0,"cdr":0.0,"nwbv":0.738},{"group":"Nondemented","sex":"F","age":89,"educ":12,"ses":4.0,"mmse":27.0,"cdr":0.0,"nwbv":0.733},{"group":"Nondemented","sex":"F","age":69,"educ":13,"ses":4.0,"mmse":30.0,"cdr":0.0,"nwbv":0.789},{"group":"Nondemented","sex":"F","age":70,"educ":13,"ses":4.0,"mmse":30.0,"cdr":0.0,"nwbv":0.783},{"group":"Nondemented","sex":"F","age":73,"educ":13,"ses":4.0,"mmse":30.0,"cdr":0.0,"nwbv":0.773},{"group":"Nondemented","sex":"F","age":75,"educ":13,"ses":4.0,"mmse":29.0,"cdr":0.0,"nwbv":0.778},{"group":"Demented","sex":"M","age":82,"educ":12,"ses":4.0,"mmse":27.0,"cdr":0.5,"nwbv":0.729},{"group":"Demented","sex":"M","age":85,"educ":12,"ses":4.0,"mmse":29.0,"cdr":0.5,"nwbv":0.717},{"group":"Demented","sex":"M","age":88,"educ":12,"ses":4.0,"mmse":26.0,"cdr":0.5,"nwbv":0.709},{"group":"Demented","sex":"M","age":89,"educ":12,"ses":4.0,"mmse":26.0,"cdr":0.5,"nwbv":0.706},{"group":"Demented","sex":"F","age":81,"educ":18,"ses":2.0,"mmse":26.0,"cdr":0.5,"nwbv":0.742},{"group":"Demented","sex":"F","age":83,"educ":18,"ses":2.0,"mmse":25.0,"cdr":0.5,"nwbv":0.733},{"group":"Demented","sex":"M","age":84,"educ":6,"ses":4.0,"mmse":25.0,"cdr":0.5,"nwbv":0.727},{"group":"Demented","sex":"M","age":86,"educ":6,"ses":4.0,"mmse":27.0,"cdr":0.5,"nwbv":0.724},{"group":"Demented","sex":"M","age":88,"educ":6,"ses":4.0,"mmse":23.0,"cdr":0.5,"nwbv":0.713},{"group":"Converted","sex":"F","age":71,"educ":16,"ses":1.0,"mmse":27.0,"cdr":0.0,"nwbv":0.771},{"group":"Converted","sex":"F","age":73,"educ":16,"ses":1.0,"mmse":28.0,"cdr":0.0,"nwbv":0.768},{"group":"Converted","sex":"F","age":75,"educ":16,"ses":1.0,"mmse":28.0,"cdr":0.5,"nwbv":0.76},{"group":"Nondemented","sex":"F","age":70,"educ":17,"ses":3.0,"mmse":29.0,"cdr":0.0,"nwbv":0.766},{"group":"Nondemented","sex":"F","age":73,"educ":17,"ses":3.0,"mmse":29.0,"cdr":0.0,"nwbv":0.748},{"group":"Demented","sex":"F","age":72,"educ":12,"ses":4.0,"mmse":26.0,"cdr":0.5,"nwbv":0.777},{"group":"Demented","sex":"F","age":73,"educ":12,"ses":4.0,"mmse":26.0,"cdr":0.5,"nwbv":0.757},{"group":"Demented","sex":"M","age":68,"educ":14,"ses":4.0,"mmse":21.0,"cdr":1.0,"nwbv":0.685},{"group":"Demented","sex":"M","age":69,"educ":14,"ses":4.0,"mmse":15.0,"cdr":1.0,"nwbv":0.678},{"group":"Demented","sex":"M","age":71,"educ":14,"ses":4.0,"mmse":22.0,"cdr":1.0,"nwbv":0.679},{"group":"Nondemented","sex":"F","age":75,"educ":18,"ses":1.0,"mmse":30.0,"cdr":0.0,"nwbv":0.737},{"group":"Nondemented","sex":"F","age":77,"educ":18,"ses":1.0,"mmse":29.0,"cdr":0.0,"nwbv":0.731},{"group":"Demented","sex":"F","age":83,"educ":15,"ses":2.0,"mmse":20.0,"cdr":0.5,"nwbv":0.75},{"group":"Demented","sex":"F","age":85,"educ":15,"ses":2.0,"mmse":22.0,"cdr":1.0,"nwbv":0.748},{"group":"Nondemented","sex":"F","age":77,"educ":16,"ses":2.0,"mmse":29.0,"cdr":0.0,"nwbv":0.723},{"group":"Nondemented","sex":"F","age":78,"educ":16,"ses":2.0,"mmse":27.0,"cdr":0.0,"nwbv":0.727},{"group":"Demented","sex":"M","age":66,"educ":16,"ses":1.0,"mmse":19.0,"cdr":1.0,"nwbv":0.711},{"group":"Demented","sex":"M","age":66,"educ":16,"ses":1.0,"mmse":21.0,"cdr":1.0,"nwbv":0.703},{"group":"Demented","sex":"M","age":68,"educ":16,"ses":1.0,"mmse":19.0,"cdr":1.0,"nwbv":0.691},{"group":"Demented","sex":"M","age":68,"educ":16,"ses":1.0,"mmse":7.0,"cdr":1.0,"nwbv":0.682},{"group":"Demented","sex":"M","age":69,"educ":16,"ses":1.0,"mmse":4.0,"cdr":1.0,"nwbv":0.676},{"group":"Nondemented","sex":"F","age":69,"educ":16,"ses":3.0,"mmse":30.0,"cdr":0.0,"nwbv":0.794},{"group":"Nondemented","sex":"F","age":70,"educ":16,"ses":3.0,"mmse":30.0,"cdr":0.0,"nwbv":0.791},{"group":"Nondemented","sex":"F","age":71,"educ":16,"ses":3.0,"mmse":30.0,"cdr":0.0,"nwbv":0.788},{"group":"Demented","sex":"M","age":71,"educ":12,"ses":4.0,"mmse":20.0,"cdr":0.5,"nwbv":0.724},{"group":"Demented","sex":"M","age":72,"educ":12,"ses":4.0,"mmse":17.0,"cdr":1.0,"nwbv":0.695},{"group":"Nondemented","sex":"F","age":92,"educ":23,"ses":1.0,"mmse":29.0,"cdr":0.0,"nwbv":0.701},{"group":"Nondemented","sex":"F","age":94,"educ":23,"ses":1.0,"mmse":29.0,"cdr":0.0,"nwbv":0.696},{"group":"Nondemented","sex":"F","age":97,"educ":23,"ses":1.0,"mmse":30.0,"cdr":0.0,"nwbv":0.689},{"group":"Nondemented","sex":"M","age":74,"educ":18,"ses":2.0,"mmse":29.0,"cdr":0.0,"nwbv":0.737},{"group":"Nondemented","sex":"M","age":78,"educ":18,"ses":2.0,"mmse":30.0,"cdr":0.0,"nwbv":0.703},{"group":"Nondemented","sex":"F","age":82,"educ":16,"ses":3.0,"mmse":29.0,"cdr":0.0,"nwbv":0.76},{"group":"Nondemented","sex":"F","age":84,"educ":16,"ses":3.0,"mmse":28.0,"cdr":0.0,"nwbv":0.744},{"group":"Converted","sex":"F","age":85,"educ":18,"ses":1.0,"mmse":29.0,"cdr":0.0,"nwbv":0.701},{"group":"Converted","sex":"F","age":87,"educ":18,"ses":1.0,"mmse":24.0,"cdr":0.5,"nwbv":0.683},{"group":"Nondemented","sex":"M","age":65,"educ":13,"ses":3.0,"mmse":29.0,"cdr":0.0,"nwbv":0.837},{"group":"Nondemented","sex":"M","age":67,"educ":13,"ses":3.0,"mmse":27.0,"cdr":0.0,"nwbv":0.827},{"group":"Nondemented","sex":"F","age":71,"educ":14,"ses":2.0,"mmse":28.0,"cdr":0.0,"nwbv":0.756},{"group":"Nondemented","sex":"F","age":73,"educ":14,"ses":2.0,"mmse":30.0,"cdr":0.0,"nwbv":0.739},{"group":"Nondemented","sex":"F","age":81,"educ":12,"ses":2.0,"mmse":30.0,"cdr":0.0,"nwbv":0.755},{"group":"Nondemented","sex":"F","age":83,"educ":12,"ses":2.0,"mmse":29.0,"cdr":0.0,"nwbv":0.757},{"group":"Nondemented","sex":"F","age":85,"educ":12,"ses":2.0,"mmse":30.0,"cdr":0.0,"nwbv":0.739},{"group":"Demented","sex":"M","age":78,"educ":14,"ses":3.0,"mmse":30.0,"cdr":0.5,"nwbv":0.707},{"group":"Demented","sex":"M","age":79,"educ":14,"ses":3.0,"mmse":26.0,"cdr":0.5,"nwbv":0.706},{"group":"Demented","sex":"M","age":80,"educ":14,"ses":3.0,"mmse":29.0,"cdr":0.5,"nwbv":0.695},{"group":"Demented","sex":"M","age":75,"educ":13,"ses":4.0,"mmse":29.0,"cdr":0.5,"nwbv":0.766},{"group":"Demented","sex":"M","age":78,"educ":13,"ses":4.0,"mmse":28.0,"cdr":0.5,"nwbv":0.757},{"group":"Nondemented","sex":"M","age":68,"educ":18,"ses":1.0,"mmse":30.0,"cdr":0.0,"nwbv":0.747},{"group":"Nondemented","sex":"M","age":70,"educ":18,"ses":1.0,"mmse":30.0,"cdr":0.0,"nwbv":0.738},{"group":"Nondemented","sex":"M","age":72,"educ":18,"ses":1.0,"mmse":30.0,"cdr":0.0,"nwbv":0.729},{"group":"Nondemented","sex":"F","age":79,"educ":18,"ses":2.0,"mmse":29.0,"cdr":0.0,"nwbv":0.695},{"group":"Nondemented","sex":"F","age":81,"educ":18,"ses":2.0,"mmse":30.0,"cdr":0.0,"nwbv":0.677},{"group":"Nondemented","sex":"F","age":83,"educ":18,"ses":2.0,"mmse":29.0,"cdr":0.0,"nwbv":0.688},{"group":"Demented","sex":"F","age":80,"educ":12,"ses":null,"mmse":30.0,"cdr":0.5,"nwbv":0.737},{"group":"Demented","sex":"F","age":81,"educ":12,"ses":null,"mmse":27.0,"cdr":0.5,"nwbv":0.721},{"group":"Demented","sex":"F","age":78,"educ":8,"ses":5.0,"mmse":23.0,"cdr":1.0,"nwbv":0.691},{"group":"Demented","sex":"F","age":81,"educ":8,"ses":5.0,"mmse":26.0,"cdr":0.5,"nwbv":0.694},{"group":"Demented","sex":"F","age":82,"educ":8,"ses":5.0,"mmse":18.0,"cdr":0.5,"nwbv":0.682},{"group":"Demented","sex":"M","age":61,"educ":18,"ses":1.0,"mmse":30.0,"cdr":1.0,"nwbv":0.734},{"group":"Demented","sex":"M","age":62,"educ":18,"ses":1.0,"mmse":30.0,"cdr":0.5,"nwbv":0.731},{"group":"Nondemented","sex":"M","age":67,"educ":12,"ses":4.0,"mmse":30.0,"cdr":0.0,"nwbv":0.727},{"group":"Nondemented","sex":"M","age":68,"educ":12,"ses":4.0,"mmse":29.0,"cdr":0.0,"nwbv":0.738},{"group":"Nondemented","sex":"M","age":71,"educ":12,"ses":4.0,"mmse":29.0,"cdr":0.0,"nwbv":0.724},{"group":"Nondemented","sex":"M","age":73,"educ":12,"ses":4.0,"mmse":28.0,"cdr":0.0,"nwbv":0.722},{"group":"Nondemented","sex":"F","age":88,"educ":12,"ses":3.0,"mmse":30.0,"cdr":0.0,"nwbv":0.7},{"group":"Nondemented","sex":"F","age":90,"educ":12,"ses":3.0,"mmse":29.0,"cdr":0.0,"nwbv":0.676},{"group":"Nondemented","sex":"F","age":81,"educ":18,"ses":2.0,"mmse":29.0,"cdr":0.0,"nwbv":0.687},{"group":"Nondemented","sex":"F","age":82,"educ":18,"ses":2.0,"mmse":30.0,"cdr":0.0,"nwbv":0.69},{"group":"Nondemented","sex":"M","age":80,"educ":17,"ses":1.0,"mmse":28.0,"cdr":0.0,"nwbv":0.728},{"group":"Nondemented","sex":"M","age":82,"educ":17,"ses":1.0,"mmse":29.0,"cdr":0.0,"nwbv":0.723},{"group":"Nondemented","sex":"M","age":84,"educ":17,"ses":1.0,"mmse":29.0,"cdr":0.0,"nwbv":0.717},{"group":"Nondemented","sex":"M","age":85,"educ":17,"ses":1.0,"mmse":30.0,"cdr":0.0,"nwbv":0.704},{"group":"Nondemented","sex":"M","age":86,"educ":17,"ses":1.0,"mmse":30.0,"cdr":0.0,"nwbv":0.705},{"group":"Demented","sex":"F","age":83,"educ":13,"ses":2.0,"mmse":27.0,"cdr":1.0,"nwbv":0.705},{"group":"Demented","sex":"F","age":84,"educ":13,"ses":2.0,"mmse":28.0,"cdr":1.0,"nwbv":0.695},{"group":"Nondemented","sex":"F","age":70,"educ":14,"ses":3.0,"mmse":29.0,"cdr":0.0,"nwbv":0.787},{"group":"Nondemented","sex":"F","age":72,"educ":14,"ses":3.0,"mmse":28.0,"cdr":0.0,"nwbv":0.777},{"group":"Nondemented","sex":"F","age":75,"educ":14,"ses":3.0,"mmse":28.0,"cdr":0.0,"nwbv":0.782},{"group":"Nondemented","sex":"F","age":76,"educ":14,"ses":3.0,"mmse":29.0,"cdr":0.0,"nwbv":0.774},{"group":"Nondemented","sex":"F","age":77,"educ":14,"ses":3.0,"mmse":29.0,"cdr":0.0,"nwbv":0.769},{"group":"Demented","sex":"F","age":73,"educ":8,"ses":5.0,"mmse":25.0,"cdr":0.5,"nwbv":0.743},{"group":"Demented","sex":"F","age":75,"educ":8,"ses":5.0,"mmse":22.0,"cdr":0.5,"nwbv":0.741},{"group":"Nondemented","sex":"F","age":66,"educ":18,"ses":2.0,"mmse":30.0,"cdr":0.0,"nwbv":0.725},{"group":"Nondemented","sex":"F","age":69,"educ":18,"ses":2.0,"mmse":29.0,"cdr":0.0,"nwbv":0.719},{"group":"Nondemented","sex":"F","age":71,"educ":18,"ses":2.0,"mmse":30.0,"cdr":0.0,"nwbv":0.718},{"group":"Nondemented","sex":"M","age":69,"educ":16,"ses":2.0,"mmse":28.0,"cdr":0.0,"nwbv":0.737},{"group":"Nondemented","sex":"M","age":73,"educ":16,"ses":2.0,"mmse":29.0,"cdr":0.0,"nwbv":0.722},{"group":"Nondemented","sex":"M","age":89,"educ":16,"ses":1.0,"mmse":28.0,"cdr":0.0,"nwbv":0.674},{"group":"Nondemented","sex":"M","age":91,"educ":16,"ses":1.0,"mmse":28.0,"cdr":0.0,"nwbv":0.67},{"group":"Nondemented","sex":"M","age":92,"educ":16,"ses":1.0,"mmse":30.0,"cdr":0.0,"nwbv":0.682},{"group":"Demented","sex":"F","age":69,"educ":12,"ses":4.0,"mmse":23.0,"cdr":0.5,"nwbv":0.759},{"group":"Demented","sex":"F","age":71,"educ":12,"ses":4.0,"mmse":16.0,"cdr":1.0,"nwbv":0.725},{"group":"Demented","sex":"F","age":73,"educ":12,"ses":4.0,"mmse":16.0,"cdr":1.0,"nwbv":0.696},{"group":"Demented","sex":"M","age":66,"educ":15,"ses":2.0,"mmse":25.0,"cdr":0.5,"nwbv":0.727},{"group":"Demented","sex":"M","age":68,"educ":15,"ses":2.0,"mmse":30.0,"cdr":0.5,"nwbv":0.713},{"group":"Demented","sex":"M","age":69,"educ":15,"ses":2.0,"mmse":28.0,"cdr":0.5,"nwbv":0.724},{"group":"Demented","sex":"F","age":82,"educ":12,"ses":4.0,"mmse":26.0,"cdr":0.5,"nwbv":0.695},{"group":"Demented","sex":"F","age":84,"educ":12,"ses":4.0,"mmse":26.0,"cdr":0.5,"nwbv":0.686},{"group":"Nondemented","sex":"F","age":78,"educ":8,"ses":5.0,"mmse":29.0,"cdr":0.0,"nwbv":0.756},{"group":"Nondemented","sex":"F","age":80,"educ":8,"ses":5.0,"mmse":27.0,"cdr":0.0,"nwbv":0.751},{"group":"Nondemented","sex":"F","age":63,"educ":15,"ses":2.0,"mmse":28.0,"cdr":0.0,"nwbv":0.805},{"group":"Nondemented","sex":"F","age":65,"educ":15,"ses":2.0,"mmse":28.0,"cdr":0.0,"nwbv":0.792},{"group":"Demented","sex":"F","age":96,"educ":17,"ses":1.0,"mmse":26.0,"cdr":1.0,"nwbv":0.683},{"group":"Demented","sex":"F","age":98,"educ":17,"ses":1.0,"mmse":21.0,"cdr":2.0,"nwbv":0.66},{"group":"Demented","sex":"M","age":78,"educ":12,"ses":4.0,"mmse":21.0,"cdr":1.0,"nwbv":0.672},{"group":"Demented","sex":"M","age":80,"educ":12,"ses":4.0,"mmse":20.0,"cdr":1.0,"nwbv":0.661},{"group":"Demented","sex":"M","age":70,"educ":12,"ses":2.0,"mmse":29.0,"cdr":0.5,"nwbv":0.692},{"group":"Demented","sex":"M","age":72,"educ":12,"ses":2.0,"mmse":27.0,"cdr":1.0,"nwbv":0.684},{"group":"Nondemented","sex":"M","age":73,"educ":18,"ses":2.0,"mmse":29.0,"cdr":0.0,"nwbv":0.773},{"group":"Nondemented","sex":"M","age":75,"educ":18,"ses":2.0,"mmse":29.0,"cdr":0.0,"nwbv":0.772},{"group":"Nondemented","sex":"M","age":76,"educ":18,"ses":2.0,"mmse":30.0,"cdr":0.0,"nwbv":0.758},{"group":"Nondemented","sex":"M","age":75,"educ":12,"ses":4.0,"mmse":28.0,"cdr":0.0,"nwbv":0.739},{"group":"Nondemented","sex":"M","age":78,"educ":12,"ses":4.0,"mmse":29.0,"cdr":0.0,"nwbv":0.715},{"group":"Converted","sex":"F","age":83,"educ":12,"ses":2.0,"mmse":28.0,"cdr":0.0,"nwbv":0.748},{"group":"Converted","sex":"F","age":84,"educ":12,"ses":2.0,"mmse":27.0,"cdr":0.5,"nwbv":0.728},{"group":"Nondemented","sex":"F","age":61,"educ":16,"ses":1.0,"mmse":30.0,"cdr":0.0,"nwbv":0.771},{"group":"Nondemented","sex":"F","age":63,"educ":16,"ses":1.0,"mmse":30.0,"cdr":0.0,"nwbv":0.774},{"group":"Nondemented","sex":"M","age":71,"educ":18,"ses":1.0,"mmse":30.0,"cdr":0.0,"nwbv":0.699},{"group":"Nondemented","sex":"M","age":72,"educ":18,"ses":1.0,"mmse":29.0,"cdr":0.0,"nwbv":0.687},{"group":"Nondemented","sex":"M","age":74,"educ":18,"ses":1.0,"mmse":29.0,"cdr":0.0,"nwbv":0.679},{"group":"Nondemented","sex":"F","age":89,"educ":13,"ses":3.0,"mmse":29.0,"cdr":0.0,"nwbv":0.75},{"group":"Nondemented","sex":"F","age":91,"educ":13,"ses":3.0,"mmse":28.0,"cdr":0.0,"nwbv":0.736},{"group":"Nondemented","sex":"M","age":74,"educ":16,"ses":2.0,"mmse":30.0,"cdr":0.0,"nwbv":0.729},{"group":"Nondemented","sex":"M","age":77,"educ":16,"ses":2.0,"mmse":30.0,"cdr":0.0,"nwbv":0.709},{"group":"Demented","sex":"M","age":66,"educ":12,"ses":4.0,"mmse":30.0,"cdr":0.5,"nwbv":0.78},{"group":"Demented","sex":"M","age":67,"educ":12,"ses":4.0,"mmse":28.0,"cdr":0.5,"nwbv":0.783},{"group":"Demented","sex":"F","age":80,"educ":12,"ses":null,"mmse":27.0,"cdr":0.5,"nwbv":0.762},{"group":"Demented","sex":"F","age":83,"educ":12,"ses":null,"mmse":23.0,"cdr":0.5,"nwbv":0.75},{"group":"Nondemented","sex":"F","age":77,"educ":11,"ses":4.0,"mmse":29.0,"cdr":0.0,"nwbv":0.777},{"group":"Nondemented","sex":"F","age":80,"educ":11,"ses":4.0,"mmse":30.0,"cdr":0.0,"nwbv":0.757},{"group":"Nondemented","sex":"F","age":82,"educ":11,"ses":4.0,"mmse":30.0,"cdr":0.0,"nwbv":0.76},{"group":"Nondemented","sex":"F","age":71,"educ":18,"ses":2.0,"mmse":30.0,"cdr":0.0,"nwbv":0.769},{"group":"Nondemented","sex":"F","age":74,"educ":18,"ses":2.0,"mmse":30.0,"cdr":0.0,"nwbv":0.752},{"group":"Nondemented","sex":"F","age":76,"educ":18,"ses":2.0,"mmse":30.0,"cdr":0.0,"nwbv":0.757},{"group":"Demented","sex":"M","age":82,"educ":15,"ses":3.0,"mmse":29.0,"cdr":0.5,"nwbv":0.689},{"group":"Demented","sex":"M","age":84,"educ":15,"ses":3.0,"mmse":29.0,"cdr":0.5,"nwbv":0.686},{"group":"Demented","sex":"M","age":86,"educ":15,"ses":3.0,"mmse":30.0,"cdr":0.5,"nwbv":0.681},{"group":"Converted","sex":"F","age":69,"educ":16,"ses":1.0,"mmse":30.0,"cdr":0.0,"nwbv":0.75},{"group":"Converted","sex":"F","age":74,"educ":16,"ses":1.0,"mmse":30.0,"cdr":0.5,"nwbv":0.722},{"group":"Converted","sex":"F","age":75,"educ":16,"ses":1.0,"mmse":30.0,"cdr":0.5,"nwbv":0.731},{"group":"Demented","sex":"M","age":70,"educ":16,"ses":1.0,"mmse":25.0,"cdr":0.5,"nwbv":0.696},{"group":"Demented","sex":"M","age":71,"educ":16,"ses":1.0,"mmse":17.0,"cdr":1.0,"nwbv":0.685},{"group":"Nondemented","sex":"M","age":86,"educ":12,"ses":4.0,"mmse":29.0,"cdr":0.0,"nwbv":0.703},{"group":"Nondemented","sex":"M","age":87,"educ":12,"ses":4.0,"mmse":30.0,"cdr":0.0,"nwbv":0.718},{"group":"Demented","sex":"F","age":70,"educ":11,"ses":4.0,"mmse":22.0,"cdr":1.0,"nwbv":0.722},{"group":"Demented","sex":"F","age":72,"educ":11,"ses":4.0,"mmse":21.0,"cdr":1.0,"nwbv":0.686},{"group":"Demented","sex":"M","age":77,"educ":18,"ses":1.0,"mmse":25.0,"cdr":0.5,"nwbv":0.781},{"group":"Demented","sex":"M","age":79,"educ":18,"ses":1.0,"mmse":27.0,"cdr":0.5,"nwbv":0.781},{"group":"Nondemented","sex":"M","age":81,"educ":11,"ses":4.0,"mmse":28.0,"cdr":0.0,"nwbv":0.67},{"group":"Nondemented","sex":"M","age":83,"educ":11,"ses":4.0,"mmse":29.0,"cdr":0.0,"nwbv":0.67},{"group":"Demented","sex":"M","age":62,"educ":12,"ses":4.0,"mmse":17.0,"cdr":0.5,"nwbv":0.732},{"group":"Demented","sex":"M","age":65,"educ":12,"ses":4.0,"mmse":17.0,"cdr":0.5,"nwbv":0.699},{"group":"Demented","sex":"F","age":76,"educ":12,"ses":3.0,"mmse":27.0,"cdr":0.5,"nwbv":0.698},{"group":"Demented","sex":"F","age":78,"educ":12,"ses":3.0,"mmse":20.0,"cdr":0.5,"nwbv":0.689},{"group":"Demented","sex":"F","age":73,"educ":13,"ses":2.0,"mmse":23.0,"cdr":0.5,"nwbv":0.725},{"group":"Demented","sex":"F","age":75,"educ":13,"ses":2.0,"mmse":28.0,"cdr":0.5,"nwbv":0.708},{"group":"Demented","sex":"F","age":76,"educ":12,"ses":null,"mmse":27.0,"cdr":0.5,"nwbv":0.727},{"group":"Demented","sex":"F","age":78,"educ":12,"ses":null,"mmse":27.0,"cdr":1.0,"nwbv":0.709},{"group":"Demented","sex":"F","age":73,"educ":12,"ses":3.0,"mmse":27.0,"cdr":0.5,"nwbv":0.769},{"group":"Demented","sex":"F","age":75,"educ":12,"ses":3.0,"mmse":28.0,"cdr":0.5,"nwbv":0.77},{"group":"Nondemented","sex":"M","age":73,"educ":20,"ses":2.0,"mmse":30.0,"cdr":0.0,"nwbv":0.758},{"group":"Nondemented","sex":"M","age":74,"educ":20,"ses":2.0,"mmse":30.0,"cdr":0.0,"nwbv":0.759},{"group":"Nondemented","sex":"M","age":76,"educ":20,"ses":2.0,"mmse":30.0,"cdr":0.0,"nwbv":0.739},{"group":"Nondemented","sex":"M","age":78,"educ":20,"ses":2.0,"mmse":29.0,"cdr":0.0,"nwbv":0.734},{"group":"Converted","sex":"F","age":67,"educ":14,"ses":4.0,"mmse":30.0,"cdr":0.0,"nwbv":0.794},{"group":"Converted","sex":"F","age":71,"educ":14,"ses":4.0,"mmse":26.0,"cdr":0.5,"nwbv":0.788},{"group":"Nondemented","sex":"F","age":81,"educ":15,"ses":2.0,"mmse":28.0,"cdr":0.0,"nwbv":0.754},{"group":"Nondemented","sex":"F","age":83,"educ":15,"ses":2.0,"mmse":29.0,"cdr":0.0,"nwbv":0.751},{"group":"Nondemented","sex":"F","age":85,"educ":15,"ses":2.0,"mmse":30.0,"cdr":0.0,"nwbv":0.741},{"group":"Demented","sex":"F","age":76,"educ":14,"ses":3.0,"mmse":25.0,"cdr":1.0,"nwbv":0.715},{"group":"Demented","sex":"F","age":78,"educ":14,"ses":3.0,"mmse":15.0,"cdr":2.0,"nwbv":0.7},{"group":"Nondemented","sex":"F","age":73,"educ":11,"ses":4.0,"mmse":30.0,"cdr":0.0,"nwbv":0.726},{"group":"Nondemented","sex":"F","age":74,"educ":11,"ses":4.0,"mmse":30.0,"cdr":0.0,"nwbv":0.705},{"group":"Nondemented","sex":"F","age":86,"educ":16,"ses":3.0,"mmse":30.0,"cdr":0.0,"nwbv":0.747},{"group":"Nondemented","sex":"F","age":88,"educ":16,"ses":3.0,"mmse":30.0,"cdr":0.0,"nwbv":0.744},{"group":"Demented","sex":"M","age":70,"educ":16,"ses":3.0,"mmse":29.0,"cdr":0.5,"nwbv":0.749},{"group":"Demented","sex":"M","age":71,"educ":16,"ses":3.0,"mmse":27.0,"cdr":0.5,"nwbv":0.75},{"group":"Nondemented","sex":"F","age":74,"educ":12,"ses":3.0,"mmse":29.0,"cdr":0.0,"nwbv":0.739},{"group":"Nondemented","sex":"F","age":75,"educ":12,"ses":3.0,"mmse":29.0,"cdr":0.0,"nwbv":0.747},{"group":"Nondemented","sex":"F","age":77,"educ":12,"ses":3.0,"mmse":29.0,"cdr":0.0,"nwbv":0.74},{"group":"Converted","sex":"M","age":79,"educ":18,"ses":1.0,"mmse":29.0,"cdr":0.0,"nwbv":0.729},{"group":"Converted","sex":"M","age":81,"educ":18,"ses":1.0,"mmse":29.0,"cdr":0.5,"nwbv":0.72},{"group":"Converted","sex":"M","age":81,"educ":18,"ses":1.0,"mmse":29.0,"cdr":0.5,"nwbv":0.717},{"group":"Converted","sex":"M","age":84,"educ":18,"ses":1.0,"mmse":29.0,"cdr":0.5,"nwbv":0.694},{"group":"Converted","sex":"M","age":86,"educ":18,"ses":1.0,"mmse":30.0,"cdr":0.5,"nwbv":0.669},{"group":"Nondemented","sex":"F","age":76,"educ":16,"ses":1.0,"mmse":28.0,"cdr":0.0,"nwbv":0.762},{"group":"Nondemented","sex":"F","age":79,"educ":16,"ses":1.0,"mmse":29.0,"cdr":0.0,"nwbv":0.739},{"group":"Nondemented","sex":"F","age":78,"educ":18,"ses":1.0,"mmse":30.0,"cdr":0.0,"nwbv":0.666},{"group":"Nondemented","sex":"F","age":80,"educ":18,"ses":1.0,"mmse":30.0,"cdr":0.0,"nwbv":0.663},{"group":"Nondemented","sex":"F","age":82,"educ":18,"ses":1.0,"mmse":29.0,"cdr":0.0,"nwbv":0.644},{"group":"Converted","sex":"F","age":65,"educ":12,"ses":2.0,"mmse":30.0,"cdr":0.5,"nwbv":0.754},{"group":"Converted","sex":"F","age":67,"educ":12,"ses":2.0,"mmse":25.0,"cdr":0.0,"nwbv":0.761},{"group":"Converted","sex":"F","age":78,"educ":12,"ses":3.0,"mmse":29.0,"cdr":0.0,"nwbv":0.731},{"group":"Converted","sex":"F","age":81,"educ":12,"ses":3.0,"mmse":28.0,"cdr":0.5,"nwbv":0.687},{"group":"Demented","sex":"F","age":70,"educ":11,"ses":4.0,"mmse":29.0,"cdr":0.5,"nwbv":0.748},{"group":"Demented","sex":"F","age":71,"educ":11,"ses":4.0,"mmse":28.0,"cdr":0.5,"nwbv":0.741},{"group":"Nondemented","sex":"M","age":74,"educ":18,"ses":2.0,"mmse":30.0,"cdr":0.0,"nwbv":0.68},{"group":"Nondemented","sex":"M","age":78,"educ":18,"ses":2.0,"mmse":27.0,"cdr":0.0,"nwbv":0.663},{"group":"Demented","sex":"M","age":74,"educ":18,"ses":2.0,"mmse":28.0,"cdr":0.5,"nwbv":0.739},{"group":"Demented","sex":"M","age":75,"educ":18,"ses":2.0,"mmse":30.0,"cdr":0.5,"nwbv":0.737},{"group":"Nondemented","sex":"F","age":73,"educ":16,"ses":2.0,"mmse":29.0,"cdr":0.0,"nwbv":0.786},{"group":"Nondemented","sex":"F","age":75,"educ":16,"ses":2.0,"mmse":28.0,"cdr":0.0,"nwbv":0.767},{"group":"Demented","sex":"F","age":67,"educ":16,"ses":1.0,"mmse":29.0,"cdr":0.5,"nwbv":0.766},{"group":"Demented","sex":"F","age":68,"educ":16,"ses":1.0,"mmse":29.0,"cdr":0.5,"nwbv":0.733},{"group":"Demented","sex":"F","age":76,"educ":16,"ses":3.0,"mmse":26.0,"cdr":0.5,"nwbv":0.705},{"group":"Demented","sex":"F","age":78,"educ":16,"ses":3.0,"mmse":27.0,"cdr":0.5,"nwbv":0.69},{"group":"Demented","sex":"F","age":81,"educ":16,"ses":3.0,"mmse":25.0,"cdr":0.5,"nwbv":0.687},{"group":"Nondemented","sex":"F","age":65,"educ":18,"ses":2.0,"mmse":30.0,"cdr":0.0,"nwbv":0.812},{"group":"Nondemented","sex":"F","age":68,"educ":18,"ses":2.0,"mmse":29.0,"cdr":0.0,"nwbv":0.795},{"group":"Nondemented","sex":"F","age":69,"educ":16,"ses":3.0,"mmse":29.0,"cdr":0.0,"nwbv":0.819},{"group":"Nondemented","sex":"F","age":71,"educ":16,"ses":3.0,"mmse":28.0,"cdr":0.0,"nwbv":0.81},{"group":"Nondemented","sex":"F","age":89,"educ":18,"ses":2.0,"mmse":30.0,"cdr":0.0,"nwbv":0.746},{"group":"Nondemented","sex":"F","age":91,"educ":18,"ses":2.0,"mmse":30.0,"cdr":0.0,"nwbv":0.741},{"group":"Nondemented","sex":"F","age":93,"educ":18,"ses":2.0,"mmse":29.0,"cdr":0.0,"nwbv":0.723},{"group":"Converted","sex":"M","age":77,"educ":16,"ses":1.0,"mmse":30.0,"cdr":0.0,"nwbv":0.716},{"group":"Converted","sex":"M","age":79,"educ":16,"ses":1.0,"mmse":30.0,"cdr":0.5,"nwbv":0.708},{"group":"Converted","sex":"F","age":68,"educ":16,"ses":3.0,"mmse":30.0,"cdr":0.0,"nwbv":0.799},{"group":"Converted","sex":"F","age":73,"educ":16,"ses":3.0,"mmse":29.0,"cdr":0.5,"nwbv":0.771},{"group":"Demented","sex":"F","age":80,"educ":15,"ses":2.0,"mmse":20.0,"cdr":1.0,"nwbv":0.685},{"group":"Demented","sex":"F","age":82,"educ":15,"ses":2.0,"mmse":20.0,"cdr":1.0,"nwbv":0.698},{"group":"Nondemented","sex":"F","age":77,"educ":13,"ses":2.0,"mmse":29.0,"cdr":0.0,"nwbv":0.769},{"group":"Nondemented","sex":"F","age":78,"educ":13,"ses":2.0,"mmse":29.0,"cdr":0.0,"nwbv":0.769},{"group":"Nondemented","sex":"F","age":80,"educ":13,"ses":2.0,"mmse":28.0,"cdr":0.0,"nwbv":0.762},{"group":"Nondemented","sex":"F","age":82,"educ":13,"ses":2.0,"mmse":30.0,"cdr":0.0,"nwbv":0.747},{"group":"Nondemented","sex":"F","age":81,"educ":13,"ses":2.0,"mmse":29.0,"cdr":0.0,"nwbv":0.737},{"group":"Nondemented","sex":"F","age":83,"educ":13,"ses":2.0,"mmse":30.0,"cdr":0.0,"nwbv":0.732},{"group":"Demented","sex":"F","age":73,"educ":12,"ses":3.0,"mmse":30.0,"cdr":0.5,"nwbv":0.72},{"group":"Demented","sex":"F","age":75,"educ":12,"ses":3.0,"mmse":27.0,"cdr":1.0,"nwbv":0.714},{"group":"Nondemented","sex":"F","age":66,"educ":18,"ses":2.0,"mmse":29.0,"cdr":0.0,"nwbv":0.785},{"group":"Nondemented","sex":"F","age":68,"educ":18,"ses":2.0,"mmse":29.0,"cdr":0.0,"nwbv":0.772},{"group":"Nondemented","sex":"F","age":69,"educ":18,"ses":2.0,"mmse":29.0,"cdr":0.0,"nwbv":0.77},{"group":"Nondemented","sex":"F","age":75,"educ":18,"ses":1.0,"mmse":29.0,"cdr":0.0,"nwbv":0.75},{"group":"Nondemented","sex":"F","age":77,"educ":18,"ses":1.0,"mmse":28.0,"cdr":0.0,"nwbv":0.713},{"group":"Nondemented","sex":"F","age":78,"educ":18,"ses":1.0,"mmse":30.0,"cdr":0.0,"nwbv":0.748},{"group":"Nondemented","sex":"F","age":81,"educ":18,"ses":1.0,"mmse":30.0,"cdr":0.0,"nwbv":0.739},{"group":"Demented","sex":"F","age":73,"educ":12,"ses":2.0,"mmse":19.0,"cdr":1.0,"nwbv":0.728},{"group":"Demented","sex":"F","age":75,"educ":12,"ses":2.0,"mmse":18.0,"cdr":1.0,"nwbv":0.657},{"group":"Nondemented","sex":"F","age":73,"educ":15,"ses":4.0,"mmse":29.0,"cdr":0.0,"nwbv":0.697},{"group":"Nondemented","sex":"F","age":76,"educ":15,"ses":4.0,"mmse":29.0,"cdr":0.0,"nwbv":0.68},{"group":"Demented","sex":"F","age":73,"educ":14,"ses":3.0,"mmse":29.0,"cdr":0.5,"nwbv":0.757},{"group":"Demented","sex":"F","age":76,"educ":14,"ses":3.0,"mmse":28.0,"cdr":0.5,"nwbv":0.764},{"group":"Demented","sex":"M","age":76,"educ":12,"ses":null,"mmse":27.0,"cdr":0.5,"nwbv":0.705},{"group":"Demented","sex":"M","age":78,"educ":12,"ses":null,"mmse":29.0,"cdr":1.0,"nwbv":0.704},{"group":"Nondemented","sex":"M","age":77,"educ":16,"ses":1.0,"mmse":29.0,"cdr":0.0,"nwbv":0.734},{"group":"Nondemented","sex":"M","age":79,"educ":16,"ses":1.0,"mmse":30.0,"cdr":0.0,"nwbv":0.736},{"group":"Nondemented","sex":"M","age":80,"educ":16,"ses":1.0,"mmse":29.0,"cdr":0.0,"nwbv":0.724},{"group":"Demented","sex":"M","age":82,"educ":14,"ses":2.0,"mmse":23.0,"cdr":0.5,"nwbv":0.678},{"group":"Demented","sex":"M","age":84,"educ":14,"ses":2.0,"mmse":22.0,"cdr":0.5,"nwbv":0.665},{"group":"Demented","sex":"M","age":77,"educ":20,"ses":1.0,"mmse":23.0,"cdr":1.0,"nwbv":0.756},{"group":"Demented","sex":"M","age":79,"educ":20,"ses":1.0,"mmse":25.0,"cdr":2.0,"nwbv":0.76},{"group":"Demented","sex":"M","age":78,"educ":12,"ses":3.0,"mmse":23.0,"cdr":1.0,"nwbv":0.71},{"group":"Demented","sex":"M","age":80,"educ":12,"ses":3.0,"mmse":17.0,"cdr":1.0,"nwbv":0.696},{"group":"Nondemented","sex":"F","age":71,"educ":18,"ses":1.0,"mmse":30.0,"cdr":0.0,"nwbv":0.731},{"group":"Nondemented","sex":"F","age":73,"educ":18,"ses":1.0,"mmse":30.0,"cdr":0.0,"nwbv":0.739},{"group":"Nondemented","sex":"M","age":76,"educ":16,"ses":3.0,"mmse":30.0,"cdr":0.0,"nwbv":0.769},{"group":"Nondemented","sex":"M","age":77,"educ":16,"ses":3.0,"mmse":30.0,"cdr":0.0,"nwbv":0.768},{"group":"Nondemented","sex":"M","age":81,"educ":16,"ses":3.0,"mmse":30.0,"cdr":0.0,"nwbv":0.744},{"group":"Demented","sex":"M","age":75,"educ":16,"ses":1.0,"mmse":30.0,"cdr":0.5,"nwbv":0.709},{"group":"Demented","sex":"M","age":79,"educ":16,"ses":1.0,"mmse":29.0,"cdr":0.5,"nwbv":0.7},{"group":"Nondemented","sex":"M","age":60,"educ":12,"ses":4.0,"mmse":30.0,"cdr":0.0,"nwbv":0.806},{"group":"Nondemented","sex":"M","age":62,"educ":12,"ses":4.0,"mmse":30.0,"cdr":0.0,"nwbv":0.795},{"group":"Nondemented","sex":"M","age":64,"educ":12,"ses":4.0,"mmse":30.0,"cdr":0.0,"nwbv":0.794},{"group":"Demented","sex":"M","age":70,"educ":16,"ses":4.0,"mmse":26.0,"cdr":0.5,"nwbv":0.742},{"group":"Demented","sex":"M","age":72,"educ":16,"ses":4.0,"mmse":28.0,"cdr":0.5,"nwbv":0.732},{"group":"Demented","sex":"M","age":73,"educ":16,"ses":4.0,"mmse":28.0,"cdr":0.5,"nwbv":0.731},{"group":"Converted","sex":"M","age":84,"educ":16,"ses":2.0,"mmse":30.0,"cdr":0.0,"nwbv":0.71},{"group":"Converted","sex":"M","age":87,"educ":16,"ses":2.0,"mmse":30.0,"cdr":0.0,"nwbv":0.696},{"group":"Converted","sex":"M","age":89,"educ":16,"ses":2.0,"mmse":30.0,"cdr":0.5,"nwbv":0.679},{"group":"Nondemented","sex":"M","age":68,"educ":14,"ses":3.0,"mmse":26.0,"cdr":0.0,"nwbv":0.778},{"group":"Nondemented","sex":"M","age":70,"educ":14,"ses":3.0,"mmse":28.0,"cdr":0.0,"nwbv":0.77},{"group":"Nondemented","sex":"F","age":89,"educ":14,"ses":2.0,"mmse":29.0,"cdr":0.0,"nwbv":0.756},{"group":"Nondemented","sex":"F","age":90,"educ":14,"ses":2.0,"mmse":28.0,"cdr":0.0,"nwbv":0.746},{"group":"Nondemented","sex":"F","age":93,"educ":14,"ses":2.0,"mmse":30.0,"cdr":0.0,"nwbv":0.735},{"group":"Demented","sex":"M","age":79,"educ":20,"ses":1.0,"mmse":26.0,"cdr":0.5,"nwbv":0.711},{"group":"Demented","sex":"M","age":81,"educ":20,"ses":1.0,"mmse":26.0,"cdr":0.5,"nwbv":0.691},{"group":"Demented","sex":"F","age":74,"educ":12,"ses":null,"mmse":26.0,"cdr":0.5,"nwbv":0.733},{"group":"Demented","sex":"F","age":75,"educ":12,"ses":null,"mmse":null,"cdr":1.0,"nwbv":0.742},{"group":"Demented","sex":"F","age":77,"educ":12,"ses":null,"mmse":null,"cdr":1.0,"nwbv":0.733},{"group":"Demented","sex":"M","age":73,"educ":12,"ses":null,"mmse":23.0,"cdr":0.5,"nwbv":0.698},{"group":"Demented","sex":"M","age":75,"educ":12,"ses":null,"mmse":20.0,"cdr":0.5,"nwbv":0.696},{"group":"Nondemented","sex":"F","age":66,"educ":13,"ses":2.0,"mmse":30.0,"cdr":0.0,"nwbv":0.746},{"group":"Nondemented","sex":"F","age":66,"educ":13,"ses":2.0,"mmse":30.0,"cdr":0.0,"nwbv":0.74},{"group":"Nondemented","sex":"F","age":68,"educ":13,"ses":2.0,"mmse":30.0,"cdr":0.0,"nwbv":0.74},{"group":"Nondemented","sex":"F","age":72,"educ":13,"ses":2.0,"mmse":30.0,"cdr":0.0,"nwbv":0.723},{"group":"Demented","sex":"F","age":72,"educ":16,"ses":3.0,"mmse":24.0,"cdr":0.5,"nwbv":0.733},{"group":"Demented","sex":"F","age":73,"educ":16,"ses":3.0,"mmse":21.0,"cdr":1.0,"nwbv":0.708},{"group":"Demented","sex":"M","age":80,"educ":16,"ses":1.0,"mmse":28.0,"cdr":0.5,"nwbv":0.711},{"group":"Demented","sex":"M","age":82,"educ":16,"ses":1.0,"mmse":28.0,"cdr":0.5,"nwbv":0.694},{"group":"Demented","sex":"M","age":86,"educ":16,"ses":1.0,"mmse":26.0,"cdr":0.5,"nwbv":0.675},{"group":"Nondemented","sex":"F","age":61,"educ":13,"ses":2.0,"mmse":30.0,"cdr":0.0,"nwbv":0.801},{"group":"Nondemented","sex":"F","age":63,"educ":13,"ses":2.0,"mmse":30.0,"cdr":0.0,"nwbv":0.796},{"group":"Nondemented","sex":"F","age":65,"educ":13,"ses":2.0,"mmse":30.0,"cdr":0.0,"nwbv":0.801}]